yait_aichain/__init__.py
yait_aichain/_chain.py
yait_aichain/_client.py
yait_aichain/_constants.py
yait_aichain/_role.py
yait_aichain-0.1.5.dist-info/METADATA
yait_aichain-0.1.5.dist-info/WHEEL
yait_aichain-0.1.5.dist-info/top_level.txt
yait_aichain-0.1.5.dist-info/RECORD
