Metadata-Version: 2.1
Name: yait-aichain
Version: 0.1.5
Summary: A simple Python library designed to wrap and unify AI functions from various popular services
Author: YAIT
